supercell_core/__init__.py
supercell_core/atom.py
supercell_core/calc.py
supercell_core/errors.py
supercell_core/heterostructure.py
supercell_core/heterostructure_opt.py
supercell_core/input_parsers.py
supercell_core/lattice.py
supercell_core/physics.py
supercell_core/result.py
supercell_core/tests/__init__.py
supercell_core/tests/pycharm_bug.py
supercell_core/tests/test_calc.py
supercell_core/tests/test_errors.py
supercell_core/tests/test_heterostructure.py
supercell_core/tests/test_input_parsers.py
supercell_core/tests/test_lattice.py
supercell_core/tests/test_physics.py
supercell_core-0.1.7.dist-info/LICENSE
supercell_core-0.1.7.dist-info/METADATA
supercell_core-0.1.7.dist-info/WHEEL
supercell_core-0.1.7.dist-info/top_level.txt
supercell_core-0.1.7.dist-info/RECORD
