Metadata-Version: 2.1
Name: supercell-core
Version: 0.1.7
Summary: Package for investigation of 2D van der Waals heterostructures' lattices
Home-page: https://github.com/tnecio/supercell-core
Author: Tomasz Necio
Author-email: Tomasz.Necio@fuw.edu.pl
License: GPLv3
Platform: UNKNOWN
Classifier: Programming Language :: Python :: 3
Classifier: Operating System :: OS Independent
Classifier: Intended Audience :: Science/Research
Classifier: License :: OSI Approved :: GNU General Public License v3 or later (GPLv3+)
Classifier: Topic :: Scientific/Engineering :: Physics
Requires-Dist: matplotlib
Requires-Dist: numpy
Provides-Extra: log
Requires-Dist: pandas ; extra == 'log'
